dvsa_mot_history/__init__.py
dvsa_mot_history/api.py
dvsa_mot_history/client.py
dvsa_mot_history/enums.py
dvsa_mot_history/errors.py
dvsa_mot_history/models.py
dvsa_mot_history/utils.py
dvsa_mot_history-1.0.4.dist-info/LICENSE
dvsa_mot_history-1.0.4.dist-info/METADATA
dvsa_mot_history-1.0.4.dist-info/WHEEL
dvsa_mot_history-1.0.4.dist-info/RECORD
