Metadata-Version: 2.1
Name: dvsa_mot_history
Version: 1.0.4
Summary: Python SDK for DVSA MOT History API
License: MIT
Author: tigattack
Author-email: 10629864+tigattack@users.noreply.github.com
Requires-Python: >=3.9,<4.0
Classifier: License :: OSI Approved :: MIT License
Classifier: Programming Language :: Python :: 3
Classifier: Programming Language :: Python :: 3.9
Classifier: Programming Language :: Python :: 3.10
Classifier: Programming Language :: Python :: 3.11
Classifier: Programming Language :: Python :: 3.12
Requires-Dist: aiohttp (==3.9.5)
Requires-Dist: msal (>=1.30.0,<2.0.0)
Requires-Dist: pydantic (>=2.8.2,<3.0.0)
Project-URL: Changelog, https://github.com/tigattack/dvsa-mot-history-api-py/blob/main/CHANGELOG.md
Project-URL: Issues, https://github.com/tigattack/dvsa-mot-history-api-py/issues
Project-URL: Repository, https://github.com/tigattack/dvsa-mot-history-api-py
